peperoncino/__init__.py
peperoncino/processing.py
peperoncino/processings/__init__.py
peperoncino/processings/apply_column.py
peperoncino/processings/as_category.py
peperoncino/processings/as_type.py
peperoncino/processings/assign.py
peperoncino/processings/combinations.py
peperoncino/processings/drop_columns.py
peperoncino/processings/drop_duplicates.py
peperoncino/processings/pipeline.py
peperoncino/processings/query.py
peperoncino/processings/rename_columns.py
peperoncino/processings/select.py
peperoncino/processings/stats_encoding.py
peperoncino/processings/target_encoding.py
peperoncino/utils/__init__.py
peperoncino/utils/from_list.py
peperoncino/utils/from_yaml.py
peperoncino-0.0.5.dist-info/WHEEL
peperoncino-0.0.5.dist-info/METADATA
peperoncino-0.0.5.dist-info/RECORD
