Metadata-Version: 2.1
Name: peperoncino
Version: 0.0.5
Summary: peperoncino: A library for easy data processing for pandas
Author: Junki Ishikawa
Author-email: 69guitar1015@gmail.com
Requires-Python: >=3.７,<4.0
Classifier: Programming Language :: Python :: 3
Classifier: Programming Language :: Python :: 3.7
Classifier: Programming Language :: Python :: 3.8
Requires-Dist: numpy (>=1.17,<2.0)
Requires-Dist: pandas (>=0.25.3,<0.26.0)
Requires-Dist: pyyaml (>=5.1,<6.0)
